aps_agent/VERSION
aps_agent/__init__.py
aps_agent-0.2.0.dist-info/LICENSE
aps_agent-0.2.0.dist-info/METADATA
aps_agent-0.2.0.dist-info/WHEEL
aps_agent-0.2.0.dist-info/RECORD
